scrapontology/__init__.py
scrapontology/db_client.py
scrapontology/extractor.py
scrapontology/llm_client.py
scrapontology/primitives.py
scrapontology/parsers/__init__.py
scrapontology/parsers/base_parser.py
scrapontology/parsers/pdf_parser.py
scrapontology/parsers/prompts.py
scrapontology/renderers/__init__.py
scrapontology/renderers/base.py
scrapontology/renderers/pyecharts_renderer.py
scrapontology-1.1.0.dist-info/METADATA
scrapontology-1.1.0.dist-info/WHEEL
scrapontology-1.1.0.dist-info/licenses/LICENSE
scrapontology-1.1.0.dist-info/RECORD
